repoup/__init__.py
repoup/entrypoint/__init__.py
repoup/entrypoint/aws_lambda.py
repoup/exceptions.py
repoup/lib/__init__.py
repoup/py.typed
repoup/repository/__init__.py
repoup/repository/deb.py
repoup/repository/rpm.py
repoup/storage/__init__.py
repoup/storage/s3.py
repoup-1.0.0b26.dist-info/LICENSE
repoup-1.0.0b26.dist-info/WHEEL
repoup-1.0.0b26.dist-info/METADATA
repoup-1.0.0b26.dist-info/RECORD
