Metadata-Version: 2.1
Name: repoup
Version: 1.0.0b26
Summary: Serverless package repository updater
Home-page: https://github.com/JGoutin/repoup
License: AGPL-3.0-or-later
Keywords: repository,packages,rpm
Author: J.Goutin
Author-email: jgoutin@accelize.com
Requires-Python: >=3.9,<4
Classifier: Development Status :: 4 - Beta
Classifier: Framework :: AsyncIO
Classifier: Intended Audience :: Developers
Classifier: Intended Audience :: System Administrators
Classifier: License :: OSI Approved :: GNU Affero General Public License v3 or later (AGPLv3+)
Classifier: Operating System :: POSIX :: Linux
Classifier: Programming Language :: Python :: 3
Classifier: Programming Language :: Python :: 3.9
Classifier: Programming Language :: Python :: 3.10
Classifier: Programming Language :: Python :: 3.11
Classifier: Programming Language :: Python :: 3
Classifier: Topic :: System :: Archiving :: Packaging
Classifier: Topic :: System :: Software Distribution
Classifier: Typing :: Typed
Provides-Extra: aws
Provides-Extra: deb
Provides-Extra: rpm
Provides-Extra: speedups
Requires-Dist: aioboto3; extra == "aws"
Requires-Dist: aiohttp[speedups]
Requires-Dist: createrepo_c; extra == "rpm"
Requires-Dist: python-debian; extra == "deb"
Requires-Dist: uvloop; extra == "speedups"
Project-URL: Repository, https://github.com/JGoutin/repoup
